dokusu/__init__.py
dokusu/__main__.py
dokusu/core.py
dokusu/dokusu.py
dokusu/rules.py
dokusu-0.0.5.dist-info/LICENSE
dokusu-0.0.5.dist-info/METADATA
dokusu-0.0.5.dist-info/WHEEL
dokusu-0.0.5.dist-info/top_level.txt
dokusu-0.0.5.dist-info/RECORD
