Metadata-Version: 2.1
Name: dokusu
Version: 0.0.5
Summary: A library for solving sudoku puzzles
Home-page: https://github.com/Chenkail/dokusu
Author: Chenkai Luo, Yegor Kuznetsov
Author-email: author@example.com
License: UNKNOWN
Platform: UNKNOWN
Classifier: Programming Language :: Python :: 3
Classifier: License :: OSI Approved :: GNU Affero General Public License v3
Classifier: Operating System :: OS Independent
Requires-Python: >=3.6
